trainer/__init__.py
trainer/cli.py
trainer/collator.py
trainer/config_mamba.py
trainer/data_utils.py
trainer/mamba_model.py
trainer/mixer_seq_simple.py
trainer/trainer_utils.py
mamba_safe-1.0.1.dist-info/LICENSE
mamba_safe-1.0.1.dist-info/METADATA
mamba_safe-1.0.1.dist-info/WHEEL
mamba_safe-1.0.1.dist-info/top_level.txt
mamba_safe-1.0.1.dist-info/RECORD
