Metadata-Version: 2.1
Name: mamba-safe
Version: 1.0.1
Summary: A framework to generate molecules with the mamba architecture
Home-page: https://github.com/Anri-Lombard/DrugGPT
Author: Anri Lombard
Author-email: anri.m.lombard@gmail.com
Classifier: Programming Language :: Python :: 3
Classifier: License :: OSI Approved :: MIT License
Classifier: Operating System :: OS Independent
Requires-Python: >=3.6
License-File: LICENSE
Requires-Dist: transformers
Requires-Dist: torch
Requires-Dist: accelerate
Requires-Dist: datasets
Requires-Dist: mamba-ssm
Requires-Dist: causal-conv1d
